MANIFEST.in
README
setup.py
social_commerce.egg-info/PKG-INFO
social_commerce.egg-info/SOURCES.txt
social_commerce.egg-info/dependency_links.txt
social_commerce.egg-info/not-zip-safe
social_commerce.egg-info/requires.txt
social_commerce.egg-info/top_level.txt
socialcommerce/__init__.py
socialcommerce/context_processors.py
socialcommerce/development.py
socialcommerce/manage.py
socialcommerce/pinax-requirements.txt
socialcommerce/production.py
socialcommerce/requirements.txt
socialcommerce/satchmo_settings.py
socialcommerce/settings.py
socialcommerce/urls.py
socialcommerce/apps/__init__.py
socialcommerce/apps/about/__init__.py
socialcommerce/apps/about/models.py
socialcommerce/apps/about/urls.py
socialcommerce/apps/about/views.py
socialcommerce/apps/cms/__init__.py
socialcommerce/apps/cms/appresolver.py
socialcommerce/apps/cms/context_processors.py
socialcommerce/apps/cms/exceptions.py
socialcommerce/apps/cms/middleware.py
socialcommerce/apps/cms/plugin_base.py
socialcommerce/apps/cms/plugin_pool.py
socialcommerce/apps/cms/settings.py
socialcommerce/apps/cms/signals.py
socialcommerce/apps/cms/tests.py
socialcommerce/apps/cms/urls.py
socialcommerce/apps/cms/urlutils.py
socialcommerce/apps/cms/utils.py
socialcommerce/apps/cms/views.py
socialcommerce/apps/cms/admin/__init__.py
socialcommerce/apps/cms/admin/change_list.py
socialcommerce/apps/cms/admin/forms.py
socialcommerce/apps/cms/admin/utils.py
socialcommerce/apps/cms/admin/views.py
socialcommerce/apps/cms/admin/widgets.py
socialcommerce/apps/cms/docs/screen1.png
socialcommerce/apps/cms/docs/screen2.png
socialcommerce/apps/cms/docs/screen3.png
socialcommerce/apps/cms/media/cms/css/jquery.tooltip.css
socialcommerce/apps/cms/media/cms/css/pages.css
socialcommerce/apps/cms/media/cms/css/plugin_editor.css
socialcommerce/apps/cms/media/cms/css/plugin_forms.css
socialcommerce/apps/cms/media/cms/css/rte.css
socialcommerce/apps/cms/media/cms/css/jquery/cupertino/jquery-ui.css
socialcommerce/apps/cms/media/cms/css/jquery/cupertino/images/ui-bg_diagonals-thick_90_eeeeee_40x40.png
socialcommerce/apps/cms/media/cms/css/jquery/cupertino/images/ui-bg_flat_15_cd0a0a_40x100.png
