Metadata-Version: 1.0
Name: social-commerce
Version: 0.0.5
Summary: Django project template using pinax and satchmo
Home-page: http://github.com/hbussell/social-commerce-project
Author: Harley Bussell
Author-email: modmac@gmail.com
License: GPL
Keywords: pinax-project
Platform: UNKNOWN
Classifier: License :: OSI Approved :: GNU General Public License (GPL)
Classifier: Programming Language :: Python
Classifier: Development Status :: 4 - Beta
Classifier: Intended Audience :: Developers
Classifier: Framework :: Django
Classifier: Environment :: Console
Classifier: Topic :: Software Development
Classifier: Topic :: System :: Software Distribution
